fhir_analyzer/__init__.py
fhir_analyzer/constants.py
fhir_analyzer/feature_selector.py
fhir_analyzer/fhirstore.py
fhir_analyzer/helper.py
fhir_analyzer/tmp.py
fhir_analyzer/patient_similarity/__init__.py
fhir_analyzer/patient_similarity/comparator.py
fhir_analyzer/patient_similarity/internal_types.py
fhir_analyzer/patient_similarity/patsim.py
fhir_analyzer/patient_similarity/nx_graphs/icd10_nx.gpickle
fhir_analyzer/patient_similarity/nx_graphs/snomed.gpickle
fhir_analyzer-0.0.7.dist-info/LICENSE
fhir_analyzer-0.0.7.dist-info/METADATA
fhir_analyzer-0.0.7.dist-info/WHEEL
fhir_analyzer-0.0.7.dist-info/top_level.txt
fhir_analyzer-0.0.7.dist-info/RECORD
