Metadata-Version: 2.1
Name: fhir-analyzer
Version: 0.0.7
Summary: A small FHIR package
Author-email: Till Rostalski <tillrostalski@gmail.com>
Project-URL: Homepage, https://github.com/trostalski/fhir_analyzer
Classifier: Programming Language :: Python :: 3
Classifier: License :: OSI Approved :: MIT License
Classifier: Operating System :: OS Independent
Requires-Python: >=3.9
License-File: LICENSE
Requires-Dist: fhir.resources
Requires-Dist: pandas
Requires-Dist: fhirpathpy
Requires-Dist: networkx
Requires-Dist: nxontology
Provides-Extra: dev
Requires-Dist: pytest ; extra == 'dev'
Requires-Dist: twine ; extra == 'dev'
